{
    "entities": [
        {
            "name": "Investment in Education and Training",
            "type": "Policy Initiative",
            "description": "Investing in education and training programs that focus on developing high-demand skills such as critical thinking, problem-solving, and digital literacy.",
            "attributes": {}
        },
        {
            "name": "TRUCK DRIVERS",
            "type": "Occupational Group",
            "description": "A group of workers at risk of being displaced by autonomous vehicles",
            "attributes": {}
        },
        {
            "name": "AI",
            "type": "Technology",
            "description": "Artificial Intelligence (AI) is a branch of computer science that aims to create software or machines that exhibit human-like intelligence.",
            "attributes": {}
        },
        {
            "name": "DOCTORS",
            "type": "medical professionals",
            "description": "Professionals who can benefit from AI-powered tools to enhance their diagnostic capabilities",
            "attributes": {}
        },
        {
            "name": "Economic Growth",
            "type": "Economic Phenomenon",
            "description": "Economic growth refers to the increase in the capacity of an economy to produce goods and services, compared from one period of time to another.",
            "attributes": {}
        },
        {
            "name": "Collaboration",
            "type": "Social Activity",
            "description": "Collaboration involves working together to achieve a common goal or solve a problem.",
            "attributes": {}
        },
        {
            "name": "informed decisions",
            "type": "Insights",
            "description": "Informed decisions are based on analyzed data and insights provided by AI-powered tools.",
            "attributes": {}
        },
        {
            "name": "EDUCATION AND TRAINING PROGRAMS",
            "type": "Initiatives",
            "description": "Initiatives that can help workers develop skills needed to thrive in a job market influenced by AI",
            "attributes": {}
        },
        {
            "name": "job satisfaction",
            "type": "Emotional Well-being",
            "description": "Job satisfaction refers to the positive emotional attitude and contentment that employees feel towards their job.",
            "attributes": {}
        },
        {
            "name": "new industries and job opportunities",
            "type": "Economic Outcome",
            "description": "New industries and job opportunities are economic outcomes resulting from the creation of new sectors or roles.",
            "attributes": {}
        },
        {
            "name": "critical thinking",
            "type": "Skill",
            "description": "The ability to analyze information, reason logically, and make judgments.",
            "attributes": {}
        },
        {
            "name": "Storage",
            "type": "Activity",
            "description": "The temporary or permanent holding of goods in facilities such as warehouses.",
            "attributes": {}
        },
        {
            "name": "Tasks",
            "type": "Job Activities",
            "description": "A wide range of tasks that human workers are responsible for, from simple to complex.",
            "attributes": {}
        },
        {
            "name": "hazardous or physically demanding tasks",
            "type": "Tasks",
            "description": "Involving risks to health and safety, requiring significant physical effort.",
            "attributes": {}
        },
        {
            "name": "Job Market",
            "type": "Economic Sector",
            "description": "The job market is a system that matches employers with employees and determines the supply and demand for labor.",
            "attributes": {}
        },
        {
            "name": "low-skilled workers",
            "type": "Demographic Group",
            "description": "Low-skilled workers are individuals who typically have limited education or specialized training and perform jobs that require minimal skills.",
            "attributes": {}
        },
        {
            "name": "Legal Industry",
            "type": "Industry",
            "description": "The legal industry encompasses all activities related to the practice of law, including providing legal advice, representation in court, and other legal services.",
            "attributes": {}
        },
        {
            "name": "POLICYMAKERS",
            "type": "Leaders",
            "description": "Individuals who play a crucial role in addressing the social and economic implications of AI and ensuring that workers are equipped with the necessary skills and training",
            "attributes": {}
        },
        {
            "name": "EDUCATORS",
            "type": "Instructors",
            "description": "Individuals who play a crucial role in developing and implementing education and training programs to equip workers with the skills needed to thrive in a job market influenced by AI",
            "attributes": {}
        },
        {
            "name": "INCOME INEQUALITY",
            "type": "Social and Economic Issue",
            "description": "A potential outcome of widespread job displacement due to AI, which can arise from the uneven distribution of job opportunities and economic benefits",
            "attributes": {}
        },
        {
            "name": "PROBLEM-SOLVING",
            "type": "Skill",
            "description": "A skill that is in high demand as AI technologies become more widespread, essential for workers to thrive in a rapidly evolving job market",
            "attributes": {}
        },
        {
            "name": "LOGISTICS",
            "type": "Industry",
            "description": "An industry where AI and automation are leading to the displacement of low-skilled workers",
            "attributes": {}
        },
        {
            "name": "EMPLOYMENT",
            "type": "Employment Market",
            "description": "The ongoing process of people being employed in various sectors, which is being significantly impacted by the integration of AI technologies",
            "attributes": {}
        },
        {
            "name": "Delivery",
            "type": "Activity",
            "description": "The final step in logistics where goods are delivered to their intended recipients.",
            "attributes": {}
        },
        {
            "name": "digital literacy",
            "type": "Skill",
            "description": "Proficiency with technology and internet usage.",
            "attributes": {}
        },
        {
            "name": "Strategic and Creative Tasks",
            "type": "Task Type",
            "description": "Strategic and creative tasks require higher-level thinking and problem-solving skills.",
            "attributes": {}
        },
        {
            "name": "job creation",
            "type": "Process",
            "description": "The act of generating employment opportunities through economic activities and initiatives.",
            "attributes": {}
        },
        {
            "name": "problem-solving abilities",
            "type": "Skill",
            "description": "The capacity to identify, analyze, and resolve issues effectively.",
            "attributes": {}
        },
        {
            "name": "ENGINEERS",
            "type": "Professional",
            "description": "Professionals who can benefit from AI-powered tools to enhance their design capabilities",
            "attributes": {}
        },
        {
            "name": "JOB INSECURITY",
            "type": "Employment Risk",
            "description": "A potential outcome of widespread job displacement due to AI, which can arise from the uncertainty of job stability in a rapidly changing job market",
            "attributes": {}
        },
        {
            "name": "Sustainable Employment",
            "type": "Economic Phenomenon",
            "description": "Sustainable employment refers to the creation of jobs that are stable, well-paid, and contribute positively to society.",
            "attributes": {}
        },
        {
            "name": "job displacement",
            "type": "Economic Disruption",
            "description": "The phenomenon where automation and AI lead to loss of employment opportunities for human workers.",
            "attributes": {}
        },
        {
            "name": "human capabilities",
            "type": "Enhancement",
            "description": "The ability of humans to perform tasks more efficiently and effectively with the aid of artificial intelligence.",
            "attributes": {}
        },
        {
            "name": "new job opportunities",
            "type": "Innovation",
            "description": "New roles emerge due to technological advancements and AI integration.",
            "attributes": {}
        },
        {
            "name": "productivity",
            "type": "Enhancement",
            "description": "Productivity refers to the efficiency and effectiveness of work output.",
            "attributes": {}
        },
        {
            "name": "AUTOMATION",
            "type": "",
            "description": "The process of using technology to perform tasks that were previously done by humans, which is a key way AI is affecting employment",
            "attributes": {}
        },
        {
            "name": "large datasets",
            "type": "Data",
            "description": "Extensive collections of information",
            "attributes": {}
        },
        {
            "name": "balance between technological innovation and job creation",
            "type": "Strategic Goal",
            "description": "A strategic goal that aims to ensure that the benefits of AI are shared equitably among workers and society as a whole.",
            "attributes": {}
        },
        {
            "name": "productivity enhancement",
            "type": "Process",
            "description": "The improvement of efficiency and effectiveness in work processes.",
            "attributes": {}
        },
        {
            "name": "New Job Roles",
            "type": "Occupation",
            "description": "Emerging job roles in fields such as data science, machine learning, and AI research.",
            "attributes": {}
        },
        {
            "name": "diseases",
            "type": "Medical Condition",
            "description": "Diseases are disorders of structure or function in a human, animal, or plant, especially one that produces specific symptoms or that affects a specific location and is not simply a direct result of physical injury.",
            "attributes": {
                "Diagnosis Method": "AI-powered tools"
            }
        },
        {
            "name": "chatbots",
            "type": "ArtificialIntelligence",
            "description": "Chatbots are computer programs designed to simulate human conversation through text or voice interactions.",
            "attributes": {}
        },
        {
            "name": "LAWYERS",
            "type": "professionals",
            "description": "Professionals who can benefit from AI-powered tools to enhance their legal research capabilities",
            "attributes": {}
        },
        {
            "name": "complex systems",
            "type": "Concept",
            "description": "Complex systems are systems composed of many interacting components that can give rise to emergent behaviors and properties.",
            "attributes": {
                "Domain": "Engineering, Science, Technology",
                "Characteristics": "Interconnected components, Emergent behavior, Non-linear dynamics"
            }
        },
        {
            "name": "Developing, Maintaining, and Operating AI Technologies",
            "type": "Job Role",
            "description": "These roles involve the creation, upkeep, and operation of artificial intelligence systems.",
            "attributes": {}
        },
        {
            "name": "diagnosing diseases",
            "type": "MedicalDiagnosis",
            "description": "The process of identifying diseases based on symptoms and medical data.",
            "attributes": {}
        },
        {
            "name": "employees",
            "type": "Workers",
            "description": "Individuals performing tasks within a business environment.",
            "attributes": {}
        },
        {
            "name": "Economic Growth, Innovation, Sustainable Employment",
            "type": "Economic Factors",
            "description": "These factors are crucial for the long-term health and stability of employment.",
            "attributes": {}
        },
        {
            "name": "machine learning",
            "type": "ArtificialIntelligenceSubfield",
            "description": "MachineLearning is a subset of AI that focuses on developing algorithms enabling systems to learn from data, make predictions or decisions without being explicitly programmed.",
            "attributes": {}
        },
        {
            "name": "legal research",
            "type": "Activity",
            "description": "Legal research involves the process of identifying and retrieving information necessary to support legal decision-making.",
            "attributes": {
                "Purpose": "Supporting legal decision-making",
                "Tools Used": "AI-powered tools"
            }
        },
        {
            "name": "WORKPLACE SAFETY",
            "type": "",
            "description": "An area where AI can improve conditions by taking on hazardous or physically demanding tasks",
            "attributes": {}
        },
        {
            "name": "Patients",
            "type": "People",
            "description": "Patients are individuals who receive medical care from doctors or other healthcare professionals.",
            "attributes": {}
        },
        {
            "name": "Rapidly Evolving Job Market",
            "type": "Economic Phenomenon",
            "description": "The rapidly evolving job market refers to the dynamic changes in employment opportunities and required skills due to technological advancements.",
            "attributes": {}
        },
        {
            "name": "Responsible AI Practices",
            "type": "Concept",
            "description": "Responsible AI practices involve the ethical and transparent use of artificial intelligence to ensure that it benefits society as a whole.",
            "attributes": {}
        },
        {
            "name": "MANUFACTURING",
            "type": "industrial-processes",
            "description": "An industry where AI and automation are leading to the displacement of low-skilled workers",
            "attributes": {}
        },
        {
            "name": "data science",
            "type": "Field",
            "description": "Data Science is the practice of extracting insights and knowledge from data using statistical and computational methods.",
            "attributes": {}
        },
        {
            "name": "repetitive and routine jobs",
            "type": "Job Type",
            "description": "Repetitive and routine jobs are tasks that involve the same actions performed repeatedly, often in a predictable manner.",
            "attributes": {}
        },
        {
            "name": "SOCIAL UNREST",
            "type": "CONFLICT",
            "description": "A potential outcome of widespread job displacement due to AI, which can arise from job insecurity and income inequality",
            "attributes": {}
        },
        {
            "name": "Healthcare Industry",
            "type": "Industry",
            "description": "The healthcare industry encompasses all services and products related to health, including hospitals, clinics, and pharmaceuticals.",
            "attributes": {}
        },
        {
            "name": "creativity",
            "type": "CognitiveFunction",
            "description": "The ability to generate new ideas and innovative solutions.",
            "attributes": {}
        },
        {
            "name": "Clients",
            "type": "Person or Organization",
            "description": "Clients are individuals or organizations that seek the services of lawyers for legal advice or representation.",
            "attributes": {}
        },
        {
            "name": "stakeholders",
            "type": "Group of Individuals or Organizations",
            "description": "Stakeholders are individuals, groups, or organizations that have an interest in the outcomes and impacts of AI technologies. They play a crucial role in shaping policies, strategies, and initiatives related to AI.",
            "attributes": {
                "Role": "Collaborators",
                "Responsibility": "Developing Strategies for Technological Innovation and Job Creation"
            }
        },
        {
            "name": "designing complex systems",
            "type": "Engineering",
            "description": "The process of creating and developing intricate systems or structures.",
            "attributes": {}
        },
        {
            "name": "CUSTOMER SERVICE",
            "type": "Support",
            "description": "An industry where AI and automation are leading to the displacement of low-skilled workers",
            "attributes": {}
        },
        {
            "name": "workers",
            "type": "Person",
            "description": "Workers are individuals who perform tasks for businesses in exchange for compensation.",
            "attributes": {}
        },
        {
            "name": "BUSINESSES",
            "type": "Organizations",
            "description": "Organizations that are integrating AI technologies and need to ensure that their workforce is equipped with the skills to thrive in a rapidly evolving job market",
            "attributes": {}
        }
    ],
    "relations": [
        [
            "EDUCATION AND TRAINING PROGRAMS",
            "involvement",
            "EDUCATORS",
            "Educators are involved in developing and implementing education and training programs to equip workers with the skills needed to thrive in a job market influenced by AI"
        ],
        [
            "AI",
            "causes",
            "new job opportunities",
            "The advancement of AI technology causes an increase in new job opportunities."
        ],
        [
            "ARTIFICIAL INTELLIGENCE (AI)",
            "enhances",
            "WORKPLACE SAFETY",
            "AI can improve workplace safety by taking on hazardous tasks"
        ],
        [
            "sustainable employment",
            "Promoted By",
            "Policymakers, Businesses, and Educators",
            "Sustainable employment is promoted by the collaborative efforts of policymakers, businesses, and educators to address challenges and ensure that workers have the necessary skills and training."
        ],
        [
            "educators",
            "Collaborates With",
            "businesses",
            "Educators collaborate with businesses to ensure workers are equipped with the skills and training needed to thrive in a rapidly evolving job market."
        ],
        [
            "customer service",
            "Enables",
            "Strategic and Creative Tasks",
            "By automating routine tasks, customer service workers can focus on more strategic and creative tasks, leading to higher job satisfaction and performance."
        ],
        [
            "doctors",
            "Uses",
            "AI-powered tools",
            "Doctors can use AI-powered tools to assist in diagnosing diseases."
        ],
        [
            "ARTIFICIAL INTELLIGENCE (AI)",
            "application",
            "DOCTORS",
            "AI can assist doctors in diagnosing diseases, enhancing their capabilities"
        ],
        [
            "employment",
            "Driven By",
            "Economic Growth, Innovation, Sustainable Employment",
            "Employment is driven by economic growth, innovation, and sustainable practices."
        ],
        [
            "Artificial Intelligence",
            "Augments",
            "Human Capabilities",
            "AI augments human capabilities, enabling workers to perform their jobs more effectively and efficiently."
        ],
        [
            "logistics",
            "Involves",
            "Delivery",
            "Logistics involves the delivery of goods as a critical part of the supply chain."
        ],
        [
            "automation",
            "Driven By",
            "AI",
            "Automation is driven by advancements in AI, which enable machines to perform complex tasks."
        ],
        [
            "customer service",
            "Is Automated By",
            "Chatbots",
            "Chatbots are being used to automate routine and repetitive tasks in customer service, such as answering frequently asked questions."
        ],
        [
            "human capabilities",
            "Enhanced By",
            "Education and Training Programs",
            "Human skills and expertise are enhanced by education and training programs that focus on developing high-demand skills."
        ],
        [
            "ai",
            "Fosters",
            "Sustainable Employment",
            "Innovation fosters sustainable employment by driving long-term economic growth and creating new opportunities."
        ],
        [
            "policymakers",
            "Ensure",
            "Equitable Benefits of AI",
            "Policymakers ensure that the benefits of AI are shared equitably among workers and society by developing strategies that balance technological innovation and job creation."
        ],
        [
            "manufacturing",
            "Affected By",
            "ai",
            "Manufacturing is affected by technological advancements that lead to automation."
        ],
        [
            "customer service",
            "Threatened By",
            "Chatbots and Virtual Assistants",
            "The rise of chatbots and virtual assistants is threatening the jobs of customer service representatives."
        ],
        [
            "lawyers",
            "Uses",
            "AI-powered Tools",
            "Lawyers use AI-powered tools to assist in conducting legal research, analyzing documents, and drafting legal briefs."
        ],
        [
            "contributes to",
            "economic growth",
            "ai",
            "AI contributes to economic growth."
        ],
        [
            "AI technologies",
            "enhance",
            "problem-solving abilities",
            "AI technologies enhance problem-solving abilities by automating, optimizing, and providing new methods to tackle complex issues."
        ],
        [
            "economic growth",
            "Supported By",
            "Businesses",
            "Economic growth is supported by businesses that contribute to the economy through innovation and job creation."
        ],
        [
            "Artificial Intelligence",
            "Threatens",
            "Low-Skilled Workers",
            "AI threatens low-skilled workers by automating tasks and displacing them from their jobs."
        ],
        [
            "income inequality",
            "Contributes To",
            "Social Unrest",
            "Income inequality can contribute to social unrest as it exacerbates the economic disparities within society."
        ],
        [
            "customer service",
            "Replaced By",
            "Chatbots and Virtual Assistants",
            "Customer service representatives are being replaced by chatbots and virtual assistants in many sectors."
        ],
        [
            "automation",
            "Occurs In",
            "Customer Service",
            "Automation is prevalent in the customer service sector, where it can handle routine inquiries and improve response times."
        ],
        [
            "employees",
            "At Risk Of Being Replaced By",
            "AI Technologies",
            "Low-skilled workers are at risk of being displaced by AI technologies."
        ],
        [
            "logistics",
            "Requires",
            "Skills and Training",
            "Logistics requires continuous investment in education and training to adapt to technological changes."
        ],
        [
            "ai",
            "Promotes",
            "Economic Growth",
            "Innovation drives economic growth by introducing new technologies and methods that enhance productivity and efficiency."
        ],
        [
            "workplace safety",
            "Affects",
            "Job Market",
            "Workplace safety is an important consideration in the evolving job market, as it impacts the skills and training needed for workers to thrive."
        ],
        [
            "complex systems",
            "Supported By",
            "AI-powered tools",
            "AI-powered tools can support engineers in designing complex systems."
        ],
        [
            "manufacturing",
            "Involves",
            "repetitive and routine jobs",
            "Manufacturing involves repetitive and routine jobs that can be automated."
        ],
        [
            "lawyers",
            "Represents",
            "Clients",
            "Lawyers represent clients in various legal matters, including court proceedings and negotiations."
        ],
        [
            "complex systems",
            "Designed By",
            "engineers",
            "AI-powered tools can assist engineers in designing complex systems."
        ],
        [
            "ai",
            "Enhances",
            "Productivity",
            "Innovation enhances productivity by enabling workers and businesses to perform tasks more efficiently and effectively."
        ],
        [
            "engineers",
            "Benefit From",
            "AI technologies",
            "Engineers benefit from AI technologies as these tools can complement their skills, enabling them to design more effectively and efficiently."
        ],
        [
            "human capabilities",
            "Required For",
            "Developing, Maintaining, and Operating AI Technologies",
            "Human skills and expertise are required for developing, maintaining, and operating AI technologies."
        ],
        [
            "ai",
            "Complements",
            "Human Skills",
            "Innovation complements human skills by providing tools and technologies that enhance workers\" capabilities."
        ],
        [
            "logistics",
            "Involves",
            "Storage",
            "Logistics involves the storage of goods to ensure they are available when needed."
        ],
        [
            "businesses",
            "Benefits From",
            "AI Technologies",
            "Businesses benefit from AI technologies by enhancing worker productivity, creativity, and problem-solving abilities."
        ],
        [
            "automation",
            "Occurs In",
            "Logistics",
            "Automation is prevalent in the logistics sector, where it can streamline processes and enhance accuracy."
        ],
        [
            "diseases",
            "Can Be Diagnosed By",
            "doctors",
            "AI-powered tools can assist doctors in diagnosing diseases."
        ],
        [
            "businesses",
            "Employs",
            "workers",
            "Businesses employ workers to carry out various tasks and contribute to the organization\"s goals."
        ],
        [
            "customer service",
            "Affected By",
            "Automation",
            "Customer service representatives are affected by automation as their roles become more automated."
        ],
        [
            "job insecurity",
            "Affects",
            "low-skilled workers",
            "Job insecurity disproportionately affects low-skilled workers, who are at higher risk of being displaced by AI technologies."
        ],
        [
            "ARTIFICIAL INTELLIGENCE (AI)",
            "influence",
            "EMPLOYMENT",
            "AI is significantly impacting employment by transforming job markets and creating new opportunities as well as challenges"
        ],
        [
            "ARTIFICIAL INTELLIGENCE (AI)",
            "requires",
            "CRITICAL THINKING",
            "AI is increasing the demand for critical thinking skills as workers need to adapt to new roles and responsibilities"
        ],
        [
            "employees",
            "Require Support From",
            "Policymakers, Businesses, and Educators",
            "Human workers require support from policymakers, businesses, and educators to ensure they are equipped with necessary skills and training."
        ],
        [
            "doctors",
            "Works In",
            "Healthcare Industry",
            "Doctors work in the healthcare industry."
        ],
        [
            "ARTIFICIAL INTELLIGENCE (AI)",
            "requires",
            "DIGITAL LITERACY",
            "AI is increasing the demand for digital literacy skills as workers need to adapt to new roles and responsibilities"
        ],
        [
            "manufacturing",
            "Contributes To",
            "new industries and job opportunities",
            "Manufacturing contributes to the creation of new industries and job opportunities through automation."
        ],
        [
            "job insecurity",
            "Caused By",
            "AI technologies",
            "Job insecurity is caused by the advancement and implementation of AI technologies."
        ],
        [
            "ARTIFICIAL INTELLIGENCE (AI)",
            "application",
            "LAWYERS",
            "AI can assist lawyers in conducting legal research, enhancing their capabilities"
        ],
        [
            "ARTIFICIAL INTELLIGENCE (AI)",
            "requires",
            "PROBLEM-SOLVING",
            "AI is increasing the demand for problem-solving skills as workers need to adapt to new roles and responsibilities"
        ],
        [
            "Artificial Intelligence",
            "Leads To",
            "Social Unrest",
            "AI can lead to social unrest due to concerns about job displacement and income inequality."
        ],
        [
            "customer service",
            "Required For",
            "Strategic and Creative Tasks",
            "Customer service representatives may be required to focus on more strategic and creative tasks as routine tasks are automated."
        ],
        [
            "Artificial Intelligence",
            "Leads To",
            "Income Inequality",
            "AI can lead to income inequality as it displaces low-skilled workers and benefits those with higher skills."
        ],
        [
            "EDUCATION AND TRAINING PROGRAMS",
            "involvement",
            "POLICYMAKERS",
            "Policymakers are involved in creating and supporting education and training programs to equip workers with the skills needed to thrive in a job market influenced by AI"
        ],
        [
            "employees",
            "Augmented By",
            "AI Technologies",
            "AI can augment human workers\" capabilities, enabling them to perform their jobs more effectively."
        ],
        [
            "policymakers",
            "Promote",
            "Economic Growth",
            "Policymakers promote economic growth by embracing AI responsibly and proactively."
        ],
        [
            "AI",
            "automation",
            "causes",
            "The application of AI in automation leads to significant changes and impacts, often causing improvements in efficiency, productivity, and operational processes."
        ],
        [
            "ARTIFICIAL INTELLIGENCE (AI)",
            "cause",
            "SOCIAL UNREST",
            "AI can lead to social unrest if job displacement results in widespread job insecurity and income inequality"
        ],
        [
            "businesses",
            "Contributes To",
            "Economic Growth",
            "Businesses contribute to economic growth by driving innovation, creating jobs, and increasing productivity."
        ],
        [
            "Artificial Intelligence",
            "Enhances",
            "Workplace Safety",
            "AI enhances workplace safety by taking on hazardous or physically demanding tasks, reducing the risk of injury for human workers."
        ],
        [
            "doctors",
            "Treats",
            "Patients",
            "Doctors treat patients to diagnose and manage their health conditions."
        ],
        [
            "ARTIFICIAL INTELLIGENCE (AI)",
            "applies_to",
            "DATA SCIENCE",
            "AI is creating new job opportunities in the field of data science"
        ],
        [
            "legal research",
            "Enhanced By",
            "AI",
            "AI can enhance the efficiency and accuracy of legal research."
        ],
        [
            "EDUCATION AND TRAINING PROGRAMS",
            "engagement",
            "BUSINESSES",
            "Businesses are involved in creating and supporting education and training programs to ensure their workforce is equipped with the skills needed to thrive in a job market influenced by AI"
        ],
        [
            "income inequality",
            "Associated With",
            "Job Insecurity",
            "Income inequality is often associated with job insecurity, as both are consequences of the displacement of workers due to AI technologies."
        ],
        [
            "AUTOMATION",
            "displacement_of",
            "LOGISTICS",
            "Automation is leading to the displacement of low-skilled workers in the logistics industry"
        ],
        [
            "AI technologies",
            "enhance",
            "productivity",
            "AI technologies enhance productivity by automating tasks, optimizing processes, and providing intelligent solutions that increase efficiency."
        ],
        [
            "truck drivers",
            "Engaged In",
            "logistics",
            "Truck drivers are engaged in the logistics and supply chain industry, where they transport goods over long distances."
        ],
        [
            "Artificial Intelligence",
            "Leads To",
            "Job Insecurity",
            "AI can lead to job insecurity as it displaces workers and creates a fear of widespread unemployment."
        ],
        [
            "manufacturing",
            "Enables",
            "strategic and creative tasks",
            "Manufacturing enables workers to focus on more strategic and creative tasks by automating routine jobs."
        ],
        [
            "ARTIFICIAL INTELLIGENCE (AI)",
            "utilization",
            "ENGINEERS",
            "AI can assist engineers in designing complex systems, enhancing their capabilities"
        ],
        [
            "logistics",
            "Involves",
            "Transportation",
            "Logistics involves the transportation of goods as a core activity."
        ],
        [
            "automation",
            "Occurs In",
            "Manufacturing",
            "Automation is prevalent in the manufacturing sector, where it can improve efficiency and reduce costs."
        ],
        [
            "Artificial Intelligence",
            "Enhances",
            "Productivity",
            "AI enhances productivity by streamlining processes, analyzing large datasets, and providing valuable insights."
        ],
        [
            "social unrest",
            "Caused By",
            "AI technologies",
            "The displacement of workers due to AI technologies can lead to job insecurity and income inequality, which in turn can cause social unrest."
        ],
        [
            "AI technologies",
            "are at risk of being displaced by",
            "low-skilled workers",
            "AI technologies are at risk of displacing low-skilled workers."
        ],
        [
            "policymakers",
            "Promote",
            "Innovation",
            "Policymakers promote innovation by embracing AI responsibly and proactively."
        ],
        [
            "ai",
            "Supports",
            "Job Creation",
            "Innovation supports job creation by fostering new industries and business models that require a skilled workforce."
        ],
        [
            "sustainable employment",
            "Supported By",
            "Responsible AI Practices",
            "Sustainable employment is supported by responsible AI practices that prioritize fairness, transparency, and accountability."
        ],
        [
            "AUTOMATION",
            "displacement_by",
            "MANUFACTURING",
            "Automation is leading to the displacement of low-skilled workers in the manufacturing industry"
        ],
        [
            "drives",
            "innovation",
            "ai",
            "Innovation in AI drives advancements and improvements in technology, leading to new applications and solutions."
        ],
        [
            "truck drivers",
            "At Risk Of Being Replaced By",
            "ai",
            "Truck drivers are at risk of being displaced by autonomous vehicles, which can perform the same tasks with potentially higher efficiency and lower costs."
        ],
        [
            "customer service",
            "Is Automated By",
            "Virtual Assistants",
            "Virtual assistants are being used to automate routine and repetitive tasks in customer service, such as handling simple inquiries."
        ],
        [
            "ARTIFICIAL INTELLIGENCE (AI)",
            "encompasses",
            "MACHINE LEARNING",
            "AI is creating new job opportunities in the field of machine learning"
        ],
        [
            "social unrest",
            "Affects",
            "low-skilled workers",
            "Low-skilled workers are at a higher risk of being displaced by AI technologies, which can contribute to social unrest."
        ],
        [
            "job insecurity",
            "Leads To",
            "social unrest",
            "Job insecurity can contribute to social unrest as affected individuals and communities express their dissatisfaction and frustration."
        ],
        [
            "educators",
            "Collaborates With",
            "policymakers",
            "Educators collaborate with policymakers to address the challenges posed by a rapidly evolving job market."
        ],
        [
            "stakeholders",
            "Promote",
            "balance between technological innovation and job creation",
            "Stakeholders promote a balance between technological innovation and job creation to ensure equitable distribution of AI\"s benefits."
        ],
        [
            "employees",
            "Perform Tasks",
            "Tasks",
            "Human workers perform a variety of tasks in their jobs."
        ],
        [
            "economic growth",
            "Enhanced By",
            "Investment in Education and Training",
            "Economic growth can be enhanced by investing in education and training programs to equip workers with the necessary skills for a rapidly evolving job market."
        ],
        [
            "policymakers",
            "Promote",
            "Sustainable Employment",
            "Policymakers promote sustainable employment by embracing AI responsibly and proactively."
        ],
        [
            "workplace safety",
            "Improved By",
            "AI",
            "AI can improve workplace safety by taking on hazardous or physically demanding tasks, reducing the risk of injury for human workers."
        ],
        [
            "ai",
            "threaten to replace",
            "truck drivers",
            "AI threatens to replace truck drivers"
        ],
        [
            "stakeholders",
            "Invest In",
            "education and training programs",
            "Stakeholders invest in education and training programs to ensure workers are equipped with the necessary skills for a rapidly evolving job market."
        ],
        [
            "educators",
            "Develops",
            "education and training programs",
            "Educators develop education and training programs that focus on developing high-demand skills such as critical thinking, problem-solving, and digital literacy."
        ],
        [
            "businesses",
            "Invests In",
            "Education and Training Programs",
            "Businesses invest in education and training programs to ensure that their workforce is equipped with the necessary skills for a rapidly evolving job market."
        ],
        [
            "customer service",
            "Complements",
            "AI Technologies",
            "AI technologies can complement human skills in customer service, enabling workers to perform their jobs more effectively and efficiently."
        ],
        [
            "automation",
            "Affects",
            "Employment",
            "Automation affects employment by displacing jobs through the use of technology while also creating new industries and opportunities."
        ],
        [
            "AI technologies",
            "creativity",
            "enhance",
            "AI technologies can enhance creativity by automating routine tasks, providing data-driven insights, and facilitating new creative processes."
        ],
        [
            "automation",
            "job displacement",
            "leads to",
            "Automation leads to job displacement."
        ],
        [
            "economic growth",
            "Supported By",
            "Educators",
            "Economic growth is supported by educators who play a crucial role in developing the skills and knowledge of the workforce."
        ],
        [
            "logistics",
            "Affected By",
            "Automation",
            "Logistics is significantly affected by automation, leading to the replacement of repetitive and routine jobs."
        ],
        [
            "income inequality",
            "Caused By",
            "AI Technologies",
            "The displacement of workers due to AI technologies is a significant cause of income inequality."
        ],
        [
            "automation",
            "Driven By",
            "Robots",
            "Automation is driven by the use of robots, which can take over repetitive and routine jobs."
        ],
        [
            "ARTIFICIAL INTELLIGENCE (AI)",
            "drives",
            "AUTOMATION",
            "AI is a driving force behind automation, which is leading to the displacement of certain jobs"
        ],
        [
            "sustainable employment",
            "Dependent On",
            "Skills and Training",
            "Sustainable employment is dependent on workers being equipped with the skills and training needed to thrive in a rapidly evolving job market."
        ],
        [
            "employment",
            "Enhanced By",
            "Skills and Training",
            "Employment is enhanced by providing workers with skills and training needed to thrive in a rapidly evolving job market."
        ],
        [
            "AI",
            "enhances",
            "productivity enhancement",
            "AI enhances productivity enhancement by automating tasks, optimizing processes, and providing data-driven insights."
        ],
        [
            "policymakers",
            "Invest In",
            "Education and Training Programs",
            "Policymakers invest in education and training programs that focus on developing high-demand skills such as critical thinking, problem-solving, and digital literacy."
        ],
        [
            "AUTOMATION",
            "impact",
            "TRUCK DRIVERS",
            "Autonomous vehicles, a form of automation, threaten to replace truck drivers"
        ],
        [
            "human capabilities",
            "Complement",
            "AI technologies",
            "Human skills and expertise complement AI technologies by enabling workers to perform their jobs more effectively and efficiently."
        ],
        [
            "employment",
            "Addressed By",
            "Policymakers, Businesses, Educators",
            "Policymakers, businesses, and educators address the challenges of ensuring workers have the skills and training needed to thrive in a rapidly evolving job market."
        ],
        [
            "ARTIFICIAL INTELLIGENCE (AI)",
            "cause",
            "JOB INSECURITY",
            "AI can lead to job insecurity if workers are displaced by automation and do not have the skills to adapt to new roles"
        ],
        [
            "AI-powered tools",
            "analyze",
            "large datasets",
            "AI-powered tools analyze large datasets."
        ],
        [
            "policymakers",
            "Collaborate With",
            "Businesses",
            "Policymakers collaborate with businesses to develop strategies that promote a balance between technological innovation and job creation."
        ],
        [
            "ai",
            "Requires",
            "Collaboration",
            "Innovation requires collaboration among stakeholders to develop and implement new ideas effectively."
        ],
        [
            "sustainable employment",
            "Driven By",
            "Economic Growth",
            "Sustainable employment can be driven by responsible economic growth that supports long-term job creation and stability."
        ],
        [
            "Artificial Intelligence",
            "Creates",
            "New Job Roles",
            "AI creates new job roles by transforming the job market and generating opportunities in emerging fields."
        ],
        [
            "lawyers",
            "Works In",
            "Legal Industry",
            "Lawyers work within the legal industry, which is a critical sector for ensuring justice and compliance with laws."
        ],
        [
            "AUTOMATION",
            "replacing",
            "CUSTOMER SERVICE REPRESENTATIVES",
            "Chatbots and virtual assistants, forms of automation, are replacing customer service representatives"
        ],
        [
            "policymakers",
            "Collaborate With",
            "Educators",
            "Policymakers collaborate with educators to develop strategies that promote a balance between technological innovation and job creation."
        ],
        [
            "AI",
            "augments",
            "automation",
            "AI augments automation by enhancing efficiency, intelligence, and adaptability in automated systems."
        ],
        [
            "legal research",
            "Conducted By",
            "lawyers",
            "AI-powered tools can assist lawyers in conducting legal research."
        ],
        [
            "engineers",
            "Use Tools",
            "AI-powered tools",
            "Engineers use AI-powered tools to assist in designing complex systems."
        ],
        [
            "economic growth",
            "Supported By",
            "Policymakers",
            "Economic growth is supported by policymakers who address challenges and ensure workers are equipped with the skills needed to thrive in a changing job market."
        ],
        [
            "educators",
            "Equips",
            "workers",
            "Educators equip workers with the skills and training needed to thrive in a rapidly evolving job market."
        ],
        [
            "ARTIFICIAL INTELLIGENCE (AI)",
            "impact",
            "EDUCATION AND TRAINING PROGRAMS",
            "AI is influencing the need for education and training programs to equip workers with new skills"
        ],
        [
            "ARTIFICIAL INTELLIGENCE (AI)",
            "cause",
            "INCOME INEQUALITY",
            "AI can lead to income inequality if the benefits of AI are not distributed equitably among workers"
        ],
        [
            "Artificial Intelligence",
            "Affects",
            "Employment",
            "AI affects employment by both displacing certain jobs through automation and creating new job opportunities."
        ],
        [
            "AUTOMATION",
            "displacement_by",
            "CUSTOMER SERVICE",
            "Automation is leading to the displacement of low-skilled workers in the customer service industry"
        ],
        [
            "policymakers",
            "Address Challenges",
            "Rapidly Evolving Job Market",
            "Policymakers address challenges related to the rapidly evolving job market by ensuring workers are equipped with necessary skills and training."
        ],
        [
            "businesses",
            "Faces Challenges From",
            "Automation",
            "Businesses face challenges from automation, particularly in sectors such as manufacturing, logistics, and customer service, where repetitive and routine jobs are being automated."
        ],
        [
            "stakeholders",
            "Ensure",
            "equitable sharing of AI benefits",
            "Stakeholders ensure that the benefits of AI are shared equitably among workers and society as a whole."
        ],
        [
            "employment",
            "Affected By",
            "AI",
            "Employment is affected by AI through automation and augmentation of human capabilities."
        ],
        [
            "employees",
            "Benefit From",
            "Workplace Safety Improvements",
            "AI can improve workplace safety by taking on hazardous tasks, reducing risks for human workers."
        ],
        [
            "job insecurity",
            "Leads To",
            "income inequality",
            "Job insecurity can lead to income inequality as workers lose their jobs and face financial instability."
        ],
        [
            "automation",
            "Driven By",
            "Machine Learning",
            "Automation is driven by machine learning, which allows systems to learn from data and make decisions or predictions."
        ],
        [
            "ARTIFICIAL INTELLIGENCE (AI)",
            "leads_to",
            "AI RESEARCH",
            "AI is creating new job opportunities in the field of AI research"
        ],
        [
            "economic growth",
            "Driven By",
            "AI",
            "Economic growth can be driven by the responsible and proactive use of AI, which has the potential to enhance productivity and innovation."
        ],
        [
            "sustainable employment",
            "Enhanced By",
            "AI",
            "AI can enhance sustainable employment by automating routine tasks, augmenting human capabilities, and enabling workers to focus on more strategic and creative tasks."
        ],
        [
            "stakeholders",
            "Collaborate With",
            "policymakers",
            "Stakeholders collaborate with policymakers, businesses, and educators to develop strategies that promote a balance between technological innovation and job creation."
        ],
        [
            "manufacturing",
            "Influenced By",
            "AI",
            "Manufacturing is influenced by AI, which plays a key role in the automation of processes."
        ]
    ]
}