{
    "entities": [
        {
            "name": "BLOOD PRESSURE",
            "type": "Vital_Signs",
            "description": "A physiological response that can be influenced by the color red, leading to increased excitement and arousal",
            "attributes": {}
        },
        {
            "name": "Advertising",
            "type": "Industry",
            "description": "The advertising industry uses various techniques to attract and engage consumers.",
            "attributes": {}
        },
        {
            "name": "meditation rooms",
            "type": "Space",
            "description": "Meditation rooms are designated spaces where individuals can practice meditation to achieve a state of peace and serenity.",
            "attributes": {
                "Purpose": "To provide a peaceful and serene environment for meditation",
                "Common Colors Used": "Cool colors like blue, green, and purple"
            }
        },
        {
            "name": "HEART RATE",
            "type": "Biological Response",
            "description": "A physiological response that can be influenced by the color red, leading to increased excitement and arousal",
            "attributes": {}
        },
        {
            "name": "Perception",
            "type": "Cognitive Process",
            "description": "The process of organizing, identifying, and interpreting sensory information.",
            "attributes": {}
        },
        {
            "name": "serotonin",
            "type": "Chemical Compound",
            "description": "Serotonin, also known as 5-hydroxytryptamine (5-HT), is a monoamine neurotransmitter. It is primarily found in the brain, blood platelets, and the digestive tract.",
            "attributes": {
                "Function": "Neurotransmitter",
                "Location": "Brain, Blood Platelets, Digestive Tract"
            }
        },
        {
            "name": "sophistication",
            "type": "Emotion/Concept",
            "description": "Sophistication refers to the quality of being complex and developed in an impressive way.",
            "attributes": {}
        },
        {
            "name": "Excitement",
            "type": "Emotion",
            "description": "A feeling of intense enthusiasm or eagerness.",
            "attributes": {}
        },
        {
            "name": "Warmth",
            "type": "Emotional Experience",
            "description": "A subjective feeling of warmth often associated with positive emotions and physical comfort.",
            "attributes": {}
        },
        {
            "name": "Relaxation",
            "type": "State",
            "description": "A mental and physical state characterized by ease, freedom from tension and anxiety, and contentment.",
            "attributes": {}
        },
        {
            "name": "EASTERN CULTURES",
            "type": "Cultural Contexts",
            "description": "Cultural context where white is associated with death and mourning",
            "attributes": {}
        },
        {
            "name": "cheerful spaces",
            "type": "Environment",
            "description": "Cheerful spaces are environments designed to evoke positive emotions and a sense of cheerfulness.",
            "attributes": {}
        },
        {
            "name": "sadness",
            "type": "Emotion/Concept",
            "description": "Sadness is the feeling of being unhappy or sorrowful.",
            "attributes": {}
        },
        {
            "name": "Creating a sense of urgency",
            "type": "Cue",
            "description": "A strategy that uses colors to prompt immediate action or response.",
            "attributes": {}
        },
        {
            "name": "death",
            "type": "concept",
            "description": "The cessation of all biological functions that sustain a living organism.",
            "attributes": {}
        },
        {
            "name": "offices",
            "type": "Location",
            "description": "Offices are spaces where work and professional activities take place, often requiring focus and concentration.",
            "attributes": {
                "Purpose": "Work and Professional Activities",
                "Atmosphere Requirement": "Focus and Concentration"
            }
        },
        {
            "name": "Green",
            "type": "Color",
            "description": "Green is often associated with nature and tranquility.",
            "attributes": {}
        },
        {
            "name": "mourning",
            "type": "Cultural Ritual",
            "description": "A practice observed during times of bereavement.",
            "attributes": {}
        },
        {
            "name": "Emotions",
            "type": "Psychological",
            "description": "Internal emotional responses to stimuli.",
            "attributes": {}
        },
        {
            "name": "authority",
            "type": "Emotion/Concept",
            "description": "Authority refers to the right or accepted power to give orders, make decisions, and enforce obedience.",
            "attributes": {}
        },
        {
            "name": "Energy",
            "type": "Emotion",
            "description": "Energy refers to the physical or mental vigor needed for activities.",
            "attributes": {}
        },
        {
            "name": "Appetite",
            "type": "Biological Function",
            "description": "The physiological drive to eat food.",
            "attributes": {}
        },
        {
            "name": "Physical reactions",
            "type": "Reactions",
            "description": "Responses or effects on the body.",
            "attributes": {}
        },
        {
            "name": "Passion",
            "type": "Emotion",
            "description": "Passion is a strong feeling of enthusiasm and excitement towards a particular interest, activity, or cause.",
            "attributes": {}
        },
        {
            "name": "Purple",
            "type": "Color",
            "description": "Purple is associated with feelings of calmness, tranquility, and relaxation.",
            "attributes": {}
        },
        {
            "name": "concentration",
            "type": "Cognitive State",
            "description": "Concentration is the ability to direct one\"s attention exclusively toward a specific object or task.",
            "attributes": {}
        },
        {
            "name": "innocence",
            "type": "Quality",
            "description": "Lack of guilt or sin; purity.",
            "attributes": {}
        },
        {
            "name": "Orange",
            "type": "Color",
            "description": "Orange is a warm color associated with energy, warmth, and passion.",
            "attributes": {}
        },
        {
            "name": "purity",
            "type": "Quality",
            "description": "The state of being free from sin or moral defect",
            "attributes": {}
        },
        {
            "name": "red workout space",
            "type": "Space",
            "description": "A red workout space is an area designed for physical exercise, often using the color red to energize and motivate users.",
            "attributes": {
                "Color": "Red",
                "Purpose": "Physical Exercise",
                "Mood Impact": "Energizing and Motivating"
            }
        },
        {
            "name": "Office",
            "type": "Room Type",
            "description": "A room in a house or building where work is done, often requiring focus and concentration.",
            "attributes": {}
        },
        {
            "name": "power",
            "type": "Emotion/Concept",
            "description": "Power is the ability or capacity to exert influence over others.",
            "attributes": {}
        },
        {
            "name": "Sense of Urgency",
            "type": "Emotion",
            "description": "A feeling of immediate need or importance.",
            "attributes": {}
        },
        {
            "name": "Home",
            "type": "Living Space",
            "description": "A home is a place where people live, typically consisting of multiple rooms and spaces.",
            "attributes": {}
        },
        {
            "name": "BLACK",
            "type": "Duality",
            "description": "Color associated with power, authority, and sophistication, but can also evoke feelings of sadness or mystery, and is versatile in conveying a wide range of emotions and meanings",
            "attributes": {}
        },
        {
            "name": "brain",
            "type": "Organ",
            "description": "The brain is the central organ of the nervous system and plays a crucial role in controlling various bodily functions, including mood, behavior, and physical reactions.",
            "attributes": {
                "Function": "Controls mood, behavior, and physical reactions"
            }
        },
        {
            "name": "WESTERN CULTURES",
            "type": "Cultural",
            "description": "Western cultures refer to the shared beliefs, behaviors, and artifacts of societies located in Europe, North America, Australia, and parts of Africa and Asia influenced by European colonialism.",
            "attributes": {}
        },
        {
            "name": "Blue",
            "type": "Color",
            "description": "Blue is associated with calmness, tranquility, and relaxation.",
            "attributes": {}
        },
        {
            "name": "WHITE",
            "type": "color",
            "description": "Color associated with purity and innocence in Western cultures, but with death and mourning in some Eastern cultures, highlighting the influence of cultural context on color perception",
            "attributes": {}
        },
        {
            "name": "blue bedroom",
            "type": "Room Type",
            "description": "A blue bedroom is a room designed with the color blue, which is known for its calming and relaxing effects. It is often used in spaces where peace and serenity are desired.",
            "attributes": {
                "Color": "Blue",
                "Purpose": "Calming and Relaxing",
                "Common Use": "Bedroom, Office"
            }
        },
        {
            "name": "Behavior",
            "type": "Human Action",
            "description": "The range of actions and mannerisms exhibited by humans.",
            "attributes": {}
        },
        {
            "name": "Stimulating appetite",
            "type": "Culinary Technique",
            "description": "Utilizing specific flavors and presentations to increase desire for food consumption.",
            "attributes": {}
        },
        {
            "name": "Bedroom",
            "type": "Room Type",
            "description": "A room in a house or apartment where people sleep.",
            "attributes": {}
        },
        {
            "name": "mystery",
            "type": "Emotion/Concept",
            "description": "Mystery refers to something that is difficult or impossible to understand or explain.",
            "attributes": {}
        },
        {
            "name": "European Colonization",
            "type": "Historical Event",
            "description": "European colonization refers to the historical process by which European powers established colonies in various parts of the world, spreading their cultural and political influence.",
            "attributes": {}
        }
    ],
    "relations": [
        [
            "bedroom",
            "Uses Color For",
            "concentration",
            "Bedrooms often use blue to promote concentration."
        ],
        [
            "RED",
            "influence",
            "HEART RATE",
            "Red can increase heart rate, leading to feelings of excitement and arousal"
        ],
        [
            "emotions",
            "Associated With",
            "cheerful spaces",
            "Positivity is often associated with the color yellow, which can evoke feelings of joy and optimism."
        ],
        [
            "orange",
            "Associated With",
            "Excitement",
            "Orange can evoke a sense of excitement."
        ],
        [
            "cheerful spaces",
            "Part Of",
            "Home",
            "A yellow kitchen is part of a home."
        ],
        [
            "blue bedroom",
            "Used In",
            "offices",
            "Blues are often used in offices to enhance focus and concentration."
        ],
        [
            "cheerful spaces",
            "Explores Effects On",
            "Mood",
            "Color psychology explores how different colors can affect mood."
        ],
        [
            "Colors",
            "Psychological well-being",
            "impact on",
            "The impact of colors on psychological well-being refers to how different hues or shades can influence mental states, emotions, and overall emotional health."
        ],
        [
            "black",
            "Associated With",
            "sadness",
            "Black can evoke feelings of sadness, often used in contexts related to mourning and loss."
        ],
        [
            "associated_with",
            "death",
            "undefine",
            "white"
        ],
        [
            "bedroom",
            "Uses Color For",
            "blue bedroom",
            "Bedrooms often use cool colors like blue, green, and purple to evoke feelings of tranquility."
        ],
        [
            "red workout space",
            "Affects Physiological State",
            "Blood Pressure",
            "The red workout space can increase blood pressure."
        ],
        [
            "emotions",
            "Elicits",
            "emotions",
            "Positivity can lead to feelings of happiness."
        ],
        [
            "WHITE",
            "association",
            "WESTERN CULTURES",
            "In Western cultures, white is associated with purity and innocence"
        ],
        [
            "cheerful spaces",
            "Explores Effects On",
            "Behavior",
            "Color psychology explores how different colors can affect behavior."
        ],
        [
            "bedroom",
            "Uses Color For",
            "blue bedroom",
            "Bedrooms often use cool colors like blue, green, and purple to evoke feelings of calmness."
        ],
        [
            "COLOR PSYCHOLOGY",
            "studies",
            "WHITE",
            "White is a subject of study in color psychology, known for its cultural significance and the influence of cultural context on its perception"
        ],
        [
            "blue bedroom",
            "Used In",
            "meditation rooms",
            "Blues are often used in meditation rooms to create a serene environment."
        ],
        [
            "cheerful spaces",
            "Leads To",
            "Feelings of Joy and Optimism",
            "Yellow can lead to feelings of joy and optimism."
        ],
        [
            "Colors",
            "Associated With",
            "Warm Colors (Red, Orange, Yellow)",
            "Warm colors like red, orange, and yellow are often associated with feelings of energy, warmth, and passion."
        ],
        [
            "blue bedroom",
            "Associated With",
            "blue bedroom",
            "Blues are associated with feelings of calmness."
        ],
        [
            "RED",
            "effect",
            "BLOOD PRESSURE",
            "Red can increase blood pressure, leading to feelings of excitement and arousal"
        ],
        [
            "serotonin",
            "Increased By",
            "cheerful spaces",
            "The presence of the yellow color has been shown to increase serotonin levels in the brain."
        ],
        [
            "cheerful spaces",
            "Popular Choice For",
            "Spaces with a Sense of Cheerfulness",
            "Yellow is a popular choice for spaces where a sense of cheerfulness is desired."
        ],
        [
            "blue bedroom",
            "Used In",
            "bedroom",
            "Blues are often used in bedrooms to create a sense of peace and serenity."
        ],
        [
            "COLOR PSYCHOLOGY",
            "studies",
            "BLACK",
            "Black is a subject of study in color psychology, known for its versatility in conveying a wide range of emotions and meanings"
        ],
        [
            "black",
            "Associated With",
            "sophistication",
            "Black is often associated with sophistication, reflecting a refined and elegant appearance."
        ],
        [
            "advertising",
            "Uses Color",
            "cheerful spaces",
            "Advertising often uses the color red to grab attention and create a sense of urgency."
        ],
        [
            "associated_with",
            "black",
            "power",
            "The term 'associated_with' when related to 'black' and referring to 'power', suggests a connection or association wherein power is linked with or characterized by black, possibly implying a specific context such as symbolism, aesthetics, or categorization in a particular field or discipline."
        ],
        [
            "emotions",
            "Desired In",
            "cheerful spaces",
            "Happiness is often desired in spaces where a sense of cheerfulness is intended, such as kitchens or living rooms."
        ],
        [
            "blue bedroom",
            "Associated With",
            "relaxation",
            "Blues are associated with feelings of relaxation."
        ],
        [
            "green",
            "Similar To",
            "blue",
            "Green is similar to blue in terms of the emotional responses they elicit."
        ],
        [
            "cheerful spaces",
            "Stimulates",
            "Appetite",
            "A yellow kitchen can stimulate appetite."
        ],
        [
            "meditation rooms",
            "Uses Color",
            "purple",
            "Meditation rooms may use purple to enhance a sense of peace and serenity."
        ],
        [
            "black",
            "Associated With",
            "authority",
            "Black is often associated with authority, symbolizing a position of control and leadership."
        ],
        [
            "black",
            "evokes",
            "mystery",
            "The term 'black' evokes a sense of mystery."
        ],
        [
            "meditation rooms",
            "Uses Color",
            "blue",
            "Meditation rooms often use blue to create a calming atmosphere."
        ],
        [
            "green",
            "Contrasts With",
            "cheerful spaces",
            "Green contrasts with yellow in terms of the emotional responses they elicit."
        ],
        [
            "red workout space",
            "Affects Mood",
            "Excitement",
            "The red workout space can increase feelings of excitement."
        ],
        [
            "COLOR PSYCHOLOGY",
            "studies",
            "RED",
            "Red is a subject of study in color psychology, known for its effects on increasing heart rate and creating a sense of urgency"
        ],
        [
            "red workout space",
            "Affects Mood",
            "Energy",
            "The red workout space can boost energy levels."
        ],
        [
            "associated_with",
            "mourning",
            "undefine",
            "white"
        ],
        [
            "Excitement",
            "Warm colors",
            "evokes",
            "The warm colors associated with excitement evoke feelings of enthusiasm and energy."
        ],
        [
            "red workout space",
            "Affects Physiological State",
            "Heart Rate",
            "The red workout space can increase heart rate."
        ],
        [
            "Colors",
            "Stimulate",
            "Appetite",
            "Warm colors like red, orange, and yellow can stimulate appetite."
        ],
        [
            "cheerful spaces",
            "Associated With",
            "Positivity",
            "Yellow is often associated with positivity."
        ],
        [
            "emotions",
            "Promoted By",
            "cheerful spaces",
            "The color yellow can promote feelings of happiness by increasing serotonin levels in the brain."
        ],
        [
            "blue bedroom",
            "Associated With",
            "Peace and Serenity",
            "Blue bedrooms are associated with feelings of peace and serenity."
        ],
        [
            "associated_with",
            "innocence",
            "undefine",
            "white"
        ],
        [
            "red workout space",
            "Uses Color",
            "Red",
            "The red workout space uses the color red to create an energizing environment."
        ],
        [
            "orange",
            "Stimulates",
            "Appetite",
            "Orange can be particularly effective in stimulating appetite."
        ],
        [
            "orange",
            "Creates Sense Of",
            "Urgency",
            "Orange can create a sense of urgency."
        ],
        [
            "black",
            "Associated With",
            "power",
            "Black is often associated with power, reflecting its strong and commanding presence."
        ],
        [
            "WHITE",
            "symbolism",
            "EASTERN CULTURES",
            "In Eastern cultures, white is associated with death and mourning"
        ],
        [
            "cheerful spaces",
            "Explores Effects On",
            "Perception",
            "Color psychology explores how different colors can affect perception."
        ],
        [
            "purple",
            "Associated With",
            "green",
            "Purple and green are both cool colors associated with feelings of calmness, tranquility, and relaxation."
        ],
        [
            "Western cultures",
            "Shares Cultural Background With",
            "European Colonization",
            "Western cultures are heavily influenced by the historical event of European colonization."
        ],
        [
            "green",
            "Similar To",
            "purple",
            "Green is similar to purple in terms of the emotional responses they elicit."
        ],
        [
            "blue bedroom",
            "Used In",
            "Bedroom",
            "Blue bedrooms are commonly used as sleeping spaces due to their calming effects."
        ],
        [
            "bedroom",
            "Uses Color For",
            "concentration",
            "Bedrooms often use blue to promote focus and concentration."
        ],
        [
            "green",
            "Contrasts With",
            "cheerful spaces",
            "Green contrasts with red in terms of the emotional responses they elicit."
        ],
        [
            "cheerful spaces",
            "Used In",
            "Advertising",
            "Red is often used in advertising to grab attention and create a sense of urgency."
        ],
        [
            "purple",
            "Associated With",
            "blue",
            "Purple and blue are both cool colors associated with feelings of calmness, tranquility, and relaxation."
        ],
        [
            "emotions",
            "Associated With",
            "emotions",
            "Happiness and positivity are often associated with each other, reflecting a positive outlook on life."
        ],
        [
            "green",
            "Contrasts With",
            "orange",
            "Green contrasts with orange in terms of the emotional responses they elicit."
        ],
        [
            "blue bedroom",
            "Used In",
            "Office",
            "Blue bedrooms are also used as offices due to their ability to promote focus and concentration."
        ],
        [
            "serotonin",
            "Associated With",
            "emotions",
            "Serotonin levels in the brain are often associated with feelings of positivity."
        ],
        [
            "associated_with",
            "authority",
            "black",
            "The authority associates black with an entity."
        ],
        [
            "cheerful spaces",
            "Associated With",
            "Happiness",
            "Yellow is often associated with happiness."
        ],
        [
            "Western cultures",
            "Influences Perception of",
            "Colors",
            "Western cultures influence how colors are perceived and reacted to, particularly the color white which is associated with purity and innocence."
        ],
        [
            "cheerful spaces",
            "Associated With",
            "Happiness and Positivity",
            "A yellow kitchen is often associated with happiness and positivity."
        ],
        [
            "associated_with",
            "black",
            "sophistication",
            "The term 'associated_with' when related to 'black' and referring to 'sophistication' implies that black is connected or linked with sophistication, suggesting a relationship of association between these two concepts."
        ],
        [
            "serotonin",
            "Associated With",
            "emotions",
            "Serotonin levels in the brain are often associated with feelings of happiness."
        ],
        [
            "black",
            "evokes",
            "sadness",
            "The color black evokes feelings of sadness."
        ],
        [
            "cheerful spaces",
            "Stimulates",
            "Appetite",
            "Yellow can stimulate appetite."
        ],
        [
            "associated_with",
            "purity",
            "undefine",
            "white"
        ],
        [
            "bedroom",
            "Uses Color For",
            "relaxation",
            "Bedrooms often use cool colors like blue, green, and purple to evoke feelings of relaxation."
        ],
        [
            "emotions",
            "Elicits",
            "emotions",
            "Positivity can lead to feelings of joy."
        ],
        [
            "COLOR PSYCHOLOGY",
            "studies",
            "YELLOW",
            "Yellow is a subject of study in color psychology, known for its effects on increasing serotonin levels and creating a sense of cheerfulness"
        ],
        [
            "Psychological Well-being",
            "Enhanced By",
            "Color Psychology",
            "Understanding the psychological effects of colors through color psychology can enhance psychological well-being by creating environments that promote well-being, creativity, and productivity."
        ],
        [
            "COLOR PSYCHOLOGY",
            "studies",
            "GREEN",
            "Green is a subject of study in color psychology, known for its calming effects and use in spaces requiring peace and serenity"
        ],
        [
            "COLOR PSYCHOLOGY",
            "studies",
            "PURPLE",
            "Purple is a subject of study in color psychology, known for its calming effects and use in spaces requiring peace and serenity"
        ],
        [
            "YELLOW",
            "affect",
            "SEROTONIN LEVELS",
            "Yellow can increase serotonin levels, leading to feelings of happiness and positivity"
        ],
        [
            "Colors",
            "Influence",
            "Mood and Mindset",
            "Colors like calming blues, energizing reds, and cheerful yellows can influence mood and mindset."
        ],
        [
            "meditation rooms",
            "Uses Color",
            "green",
            "Meditation rooms may use green to promote a sense of peace and serenity."
        ],
        [
            "COLOR PSYCHOLOGY",
            "studies",
            "BLUE",
            "Blue is a subject of study in color psychology, known for its calming effects and use in spaces requiring focus and concentration"
        ],
        [
            "emotions",
            "Elicits",
            "emotions",
            "Positivity can lead to feelings of optimism."
        ],
        [
            "Colors",
            "Associated With",
            "Cool Colors (Blue)",
            "Cool colors like blue are often associated with feelings of calmness."
        ],
        [
            "emotions",
            "Increases",
            "serotonin",
            "Positivity, when associated with yellow, can increase serotonin levels in the brain."
        ],
        [
            "cheerful spaces",
            "Stimulates",
            "Appetite",
            "Red can be particularly effective in stimulating appetite."
        ],
        [
            "black",
            "Associated With",
            "mystery",
            "Black can evoke a sense of mystery, often used in contexts related to the unknown or enigmatic."
        ],
        [
            "Colors",
            "Create",
            "Sense of Urgency",
            "Certain warm colors can create a sense of urgency."
        ],
        [
            "cheerful spaces",
            "Creates",
            "Sense of Urgency",
            "Yellow can create a sense of urgency."
        ],
        [
            "cheerful spaces",
            "Creates",
            "Sense of Urgency",
            "A yellow kitchen can create a sense of urgency."
        ],
        [
            "COLOR PSYCHOLOGY",
            "studies",
            "ORANGE",
            "Orange is a subject of study in color psychology, known for its effects on stimulating appetite and creating a sense of urgency"
        ],
        [
            "cheerful spaces",
            "Uses Colors To Create",
            "Environments",
            "Color psychology uses the understanding of color effects to create environments that promote well-being, creativity, and productivity."
        ],
        [
            "blue bedroom",
            "Promotes",
            "Focus and Concentration",
            "Blue bedrooms promote focus and concentration, making them suitable for offices."
        ],
        [
            "cheerful spaces",
            "Explores Effects On",
            "Physical Reactions",
            "Color psychology explores how different colors can affect physical reactions."
        ],
        [
            "brain",
            "Processes Chemicals",
            "serotonin",
            "The brain processes serotonin, which can be influenced by the color yellow to increase levels."
        ],
        [
            "blue bedroom",
            "Associated With",
            "blue bedroom",
            "Blues are associated with feelings of tranquility."
        ],
        [
            "Eastern cultures",
            "Influences Perception Of",
            "Colors",
            "Eastern cultures influence the perception of colors, particularly associating white with death and mourning."
        ],
        [
            "Colors",
            "Emotions",
            "evokes",
            "Colors evoke specific emotions."
        ],
        [
            "offices",
            "Uses Color",
            "blue",
            "Offices often use blue to promote focus and concentration."
        ]
    ]
}