{
  "entities": [
    {
      "name": "sense of belonging"
    },
    {
      "name": "coping mechanisms"
    },
    {
      "name": "positive psychology"
    },
    {
      "name": "engaging"
    },
    {
      "name": "experiencing"
    },
    {
      "name": "gratitude"
    },
    {
      "name": "activities"
    },
    {
      "name": "adversity"
    },
    {
      "name": "joy"
    },
    {
      "name": "satisfaction"
    },
    {
      "name": "life satisfaction"
    },
    {
      "name": "Positive emotions"
    },
    {
      "name": "fulfilling"
    },
    {
      "name": "love"
    },
    {
      "name": "joy and fulfillment"
    },
    {
      "name": "happiness"
    },
    {
      "name": "connections"
    },
    {
      "name": "stress"
    },
    {
      "name": "enhance"
    },
    {
      "name": "mental health"
    },
    {
      "name": "emotional health"
    },
    {
      "name": "filled"
    },
    {
      "name": "creative project"
    },
    {
      "name": "create"
    },
    {
      "name": "individual's path to happiness"
    },
    {
      "name": "emotional support"
    },
    {
      "name": "mechanisms"
    },
    {
      "name": "Happiness"
    },
    {
      "name": "social support networks"
    },
    {
      "name": "practicing"
    },
    {
      "name": "strive"
    },
    {
      "name": "meaning"
    },
    {
      "name": "immersion"
    },
    {
      "name": "emotions"
    },
    {
      "name": "physical health"
    },
    {
      "name": "factors that contribute to well-being"
    },
    {
      "name": "focus"
    },
    {
      "name": "positive emotions"
    },
    {
      "name": "fulfillment"
    },
    {
      "name": "acknowledging and appreciating the positive aspects of our lives"
    },
    {
      "name": "science of happiness"
    },
    {
      "name": "cultivating a sense of gratitude"
    },
    {
      "name": "promote"
    },
    {
      "name": "pursuing a passion"
    },
    {
      "name": "understanding"
    },
    {
      "name": "resilience"
    },
    {
      "name": "emotional well-being"
    },
    {
      "name": "social connections"
    },
    {
      "name": "mastering a new skill"
    },
    {
      "name": "acceptance"
    },
    {
      "name": "well-being"
    },
    {
      "name": "fostering"
    }
  ],
  "relations": [
    [
      "Positive emotions",
      "lead to",
      "well-being"
    ],
    [
      "fostering",
      "causes",
      "connections"
    ],
    [
      "create",
      "fills_with",
      "meaning"
    ],
    [
      "immersion",
      "results in",
      "satisfaction"
    ],
    [
      "joy",
      "is a type of",
      "Positive emotions"
    ],
    [
      "individual's path to happiness",
      "varies among",
      "joy and fulfillment"
    ],
    [
      "coping mechanisms",
      "cope with",
      "stress"
    ],
    [
      "Positive emotions",
      "enhance",
      "coping mechanisms"
    ],
    [
      "practicing",
      "leads_to",
      "gratitude"
    ],
    [
      "emotional well-being",
      "contributes to",
      "life satisfaction"
    ],
    [
      "activities",
      "enhance",
      "happiness"
    ],
    [
      "immersion",
      "brings",
      "fulfillment"
    ],
    [
      "experiencing",
      "results_in",
      "emotions"
    ],
    [
      "immersion",
      "involves",
      "immersion"
    ],
    [
      "factors that contribute to well-being",
      "enhances",
      "emotional well-being"
    ],
    [
      "immersion",
      "promotes",
      "happiness"
    ],
    [
      "sense of belonging",
      "is essential for",
      "emotional health"
    ],
    [
      "Positive emotions",
      "increase",
      "resilience"
    ],
    [
      "gratitude",
      "influences",
      "happiness"
    ],
    [
      "understanding",
      "reveals",
      "mechanisms"
    ],
    [
      "pursuing a passion",
      "can lead to",
      "immersion"
    ],
    [
      "Positive emotions",
      "enhances",
      "physical health"
    ],
    [
      "acknowledging and appreciating the positive aspects of our lives",
      "leads to",
      "cultivating a sense of gratitude"
    ],
    [
      "science of happiness",
      "studies",
      "factors that contribute to well-being"
    ],
    [
      "immersion",
      "requires",
      "focus"
    ],
    [
      "connections",
      "provides",
      "emotional support"
    ],
    [
      "sense of belonging",
      "is essential for",
      "mental health"
    ],
    [
      "social support networks",
      "influences",
      "happiness"
    ],
    [
      "mastering a new skill",
      "can lead to",
      "immersion"
    ],
    [
      "love",
      "is a type of",
      "Positive emotions"
    ],
    [
      "gratitude",
      "contributes to",
      "life satisfaction"
    ],
    [
      "connections",
      "provides",
      "sense of belonging"
    ],
    [
      "create",
      "fills_with",
      "satisfaction"
    ],
    [
      "satisfaction",
      "is a type of",
      "Positive emotions"
    ],
    [
      "social support networks",
      "contributes to",
      "life satisfaction"
    ],
    [
      "resilience",
      "helps in facing",
      "adversity"
    ],
    [
      "connections",
      "provides",
      "acceptance"
    ],
    [
      "strive",
      "aims_to",
      "create"
    ],
    [
      "engaging",
      "promotes",
      "activities"
    ]
  ]
}